setup.py
tictactoe/__init__.py
tictactoe/game.py
tictactoe_pkesarkar.egg-info/PKG-INFO
tictactoe_pkesarkar.egg-info/SOURCES.txt
tictactoe_pkesarkar.egg-info/dependency_links.txt
tictactoe_pkesarkar.egg-info/not-zip-safe
tictactoe_pkesarkar.egg-info/top_level.txt