Metadata-Version: 1.0
Name: tictactoe-pkesarkar
Version: 0.1
Summary: its a game
Home-page: UNKNOWN
Author: Punith Kesarkar
Author-email: punith.kesarkar@gmail.com
License: UNKNOWN
Platform: UNKNOWN
